my_lambdata/__init__.py
my_lambdata/my_mod.py
my_lambdata/my_script.py
baddfish_my_lambdata_13-1.1.dist-info/METADATA
baddfish_my_lambdata_13-1.1.dist-info/WHEEL
baddfish_my_lambdata_13-1.1.dist-info/top_level.txt
baddfish_my_lambdata_13-1.1.dist-info/RECORD
