Metadata-Version: 2.1
Name: baddfish-my-lambdata-13
Version: 1.1
Summary: For example purposes
Home-page: https://github.com/baddfish/my-lambdata-13
Author: Tony Maddalone
Author-email: tjmaddalonec@gmail.com
License: MIT
Platform: UNKNOWN
